odoo/addons/account_invoice_download_scaleway/README.rst
odoo/addons/account_invoice_download_scaleway/__init__.py
odoo/addons/account_invoice_download_scaleway/__manifest__.py
odoo/addons/account_invoice_download_scaleway/demo/scaleway.xml
odoo/addons/account_invoice_download_scaleway/i18n/account_invoice_download_scaleway.pot
odoo/addons/account_invoice_download_scaleway/i18n/es.po
odoo/addons/account_invoice_download_scaleway/i18n/it.po
odoo/addons/account_invoice_download_scaleway/models/__init__.py
odoo/addons/account_invoice_download_scaleway/models/account_invoice_download_config.py
odoo/addons/account_invoice_download_scaleway/readme/CONFIGURE.rst
odoo/addons/account_invoice_download_scaleway/readme/CONTRIBUTORS.rst
odoo/addons/account_invoice_download_scaleway/readme/DESCRIPTION.rst
odoo/addons/account_invoice_download_scaleway/readme/USAGE.rst
odoo/addons/account_invoice_download_scaleway/static/description/icon.png
odoo/addons/account_invoice_download_scaleway/static/description/index.html
odoo/addons/account_invoice_download_scaleway/views/account_invoice_download_config.xml
odoo14_addon_account_invoice_download_scaleway-14.0.1.0.1.dev10.dist-info/METADATA
odoo14_addon_account_invoice_download_scaleway-14.0.1.0.1.dev10.dist-info/WHEEL
odoo14_addon_account_invoice_download_scaleway-14.0.1.0.1.dev10.dist-info/top_level.txt
odoo14_addon_account_invoice_download_scaleway-14.0.1.0.1.dev10.dist-info/RECORD
